axju/__about__.py
axju/__init__.py
axju/__main__.py
axju/tools.py
axju/core/__init__.py
axju/core/basic.py
axju/core/mixin.py
axju/worker/__init__.py
axju/worker/django/__init__.py
axju/worker/django/__main__.py
axju/worker/django/settings.py
axju/worker/git/__init__.py
axju/worker/git/__main__.py
tests/django/__init__.py
tests/django/test_worker.py
axju-0.0.3.dist-info/LICENSE
axju-0.0.3.dist-info/METADATA
axju-0.0.3.dist-info/WHEEL
axju-0.0.3.dist-info/entry_points.txt
axju-0.0.3.dist-info/top_level.txt
axju-0.0.3.dist-info/RECORD
