Metadata-Version: 2.1
Name: axju
Version: 0.0.3
Summary: This is my personal package
Home-page: https://github.com/axju/axju
Author: Axel Juraske
Author-email: axel.juraske@short-report.de
License: MIT
Keywords: git django deploying devops
Platform: UNKNOWN
Classifier: Intended Audience :: Developers
Classifier: Operating System :: OS Independent
Classifier: Programming Language :: Python
Classifier: Programming Language :: Python :: 3.5
Classifier: Programming Language :: Python :: 3.6
Classifier: Programming Language :: Python :: 3.7
Requires-Dist: jinja2
